{
  "id": "11156145",
  "name": "Responsa Project Online (Global Jewish Database)",
  "description": "A collection of Torah literature and Jewish texts in Hebrew. Covers thousands of years of Jewish learning, including numerous works from the Responsa literature, the Bible and the Talmud, works about Jewish law and customs, and the major codes of Jewish law (such as Maimonides' Mishneh Torah and the Shulḥan ʻarukh, with its principal commentaries). Also includes the Entsiḳlopedyah Talmudit.",
  "url": "https://arch.library.nyu.edu/databases/proxy/NYU02492",
  "site_id": "873",
  "type_id": "10",
  "owner_id": "24837",
  "az_vendor_id": "-1",
  "meta": {
    "target": "0",
    "enable_proxy": 0,
    "tn_url": "",
    "tn_height": "",
    "tn_width": "",
    "more_info": "",
    "desc_pos": 1
  },
  "created": "2015-03-18 22:08:14",
  "updated": "2015-09-19 19:12:21",
  "slug_id": "635067",
  "subjects": [
    {
      "id": "59273",
      "site_id": "873",
      "name": "Hebrew & Judaic Studies",
      "ordering": "0",
      "slug_id": "481003",
      "subject_id": "59273",
      "content_id": "11156145",
      "featured": "0",
      "content_id_count": "1"
    }
  ],
  "friendly_url": "http://guides.nyu.edu/responsa"
}