{
  "id": "11156132",
  "name": "RAMBI",
  "description": "RAMBI - The Index of Articles on Jewish Studies - is a selective bibliography of articles in the various fields of Jewish studies and in the study of Eretz Israel.",
  "url": "https://arch.library.nyu.edu/databases/proxy/NYU02996",
  "site_id": "873",
  "type_id": "10",
  "owner_id": "24837",
  "az_vendor_id": "-1",
  "meta": {
    "target": "0",
    "enable_proxy": 0,
    "tn_url": "",
    "tn_height": "",
    "tn_width": "",
    "more_info": "",
    "desc_pos": 1
  },
  "created": "2015-03-18 22:08:14",
  "updated": "2015-09-19 18:51:56",
  "slug_id": "635057",
  "subjects": [
    {
      "id": "59273",
      "site_id": "873",
      "name": "Hebrew & Judaic Studies",
      "ordering": "0",
      "slug_id": "481003",
      "subject_id": "59273",
      "content_id": "11156132",
      "featured": "1",
      "content_id_count": "1"
    },
    {
      "id": "59127",
      "site_id": "873",
      "name": "Religion",
      "ordering": "0",
      "slug_id": "480960",
      "subject_id": "59127",
      "content_id": "11156132",
      "featured": "1",
      "content_id_count": "1"
    }
  ],
  "friendly_url": "http://guides.nyu.edu/RAMBI"
}