{
  "id": "11156157",
  "name": "Routledge Ebooks",
  "description": "Ebooks supplied through Routledge in various subjects such as Computer Science, Language & Literature, Mathematics & Statistics, Reference & Information Science, Urban Studies, Arts, Education, Humanities, Law, Social Sciences, and more.",
  "url": "https://arch.library.nyu.edu/databases/proxy/NYU03588",
  "site_id": "873",
  "type_id": "10",
  "owner_id": "24837",
  "az_vendor_id": "37696",
  "meta": {
    "target": "0",
    "enable_proxy": 0,
    "tn_url": "",
    "tn_height": "",
    "tn_width": "",
    "more_info": "",
    "desc_pos": 1
  },
  "created": "2015-03-18 22:08:14",
  "updated": "2015-11-12 15:18:54",
  "slug_id": "676599",
  "subjects": [
    {
      "id": "56187",
      "site_id": "873",
      "name": "Business",
      "ordering": "0",
      "slug_id": "480953",
      "subject_id": "56187",
      "content_id": "11156157",
      "featured": "0",
      "content_id_count": "1"
    },
    {
      "id": "58944",
      "site_id": "873",
      "name": "Economics",
      "ordering": "0",
      "slug_id": "480967",
      "subject_id": "58944",
      "content_id": "11156157",
      "featured": "0",
      "content_id_count": "1"
    }
  ],
  "friendly_url": "http://guides.nyu.edu/routledgeebooks",
  "az_types": [
    {
      "id": 10179,
      "name": "Ebook Collections",
      "site_id": 873
    }
  ]
}