{
  "id": "11155911",
  "name": "Methods Navigator",
  "description": "Methods Navigator equips life scientists with a new structure for discovery - enabling them to search, access and apply research methods from over 40,000 articles. Methods Navigator also has the additional feature of 120 of the most commonly used protocols.",
  "url": "https://arch.library.nyu.edu/databases/proxy/NYU03982",
  "site_id": "873",
  "type_id": "10",
  "owner_id": "24837",
  "az_vendor_id": "-1",
  "meta": {
    "target": "0",
    "enable_proxy": 0,
    "tn_url": "",
    "tn_height": "",
    "tn_width": "",
    "more_info": "",
    "desc_pos": 1
  },
  "created": "2015-03-18 22:08:13",
  "updated": "2015-11-24 22:43:57",
  "slug_id": "685150",
  "subjects": [
    {
      "id": "58946",
      "site_id": "873",
      "name": "Biology",
      "ordering": "0",
      "slug_id": "480950",
      "subject_id": "58946",
      "content_id": "11155911",
      "featured": "0",
      "content_id_count": "1"
    }
  ],
  "friendly_url": "http://guides.nyu.edu/methods"
}