{
  "id": "11155855",
  "name": "Literature Resource Center",
  "description": "Resource for research on literary topics, authors, and their works. Its coverage includes all genres and disciplines, all time periods, and all regions of the world. Includes links to: Dictionary of literary biography, Contemporary authors, Contemporary literary criticism, and more, including full texts of critical articles.",
  "url": "https://arch.library.nyu.edu/databases/proxy/NYU00111",
  "site_id": "873",
  "type_id": "10",
  "owner_id": "24837",
  "az_vendor_id": "36968",
  "meta": {
    "target": "0",
    "enable_proxy": 0,
    "tn_url": "",
    "tn_height": "",
    "tn_width": "",
    "more_info": "",
    "desc_pos": 1
  },
  "created": "2015-03-18 22:08:13",
  "updated": "2015-09-18 14:41:18",
  "slug_id": "634163",
  "subjects": [
    {
      "id": "58953",
      "site_id": "873",
      "name": "Comparative Literature",
      "ordering": "0",
      "slug_id": "480961",
      "subject_id": "58953",
      "content_id": "11155855",
      "featured": "1",
      "content_id_count": "1"
    },
    {
      "id": "59111",
      "site_id": "873",
      "name": "English Literature",
      "ordering": "0",
      "slug_id": "481016",
      "subject_id": "59111",
      "content_id": "11155855",
      "featured": "1",
      "content_id_count": "1"
    },
    {
      "id": "59300",
      "site_id": "873",
      "name": "French Literature & Language",
      "ordering": "0",
      "slug_id": "481015",
      "subject_id": "59300",
      "content_id": "11155855",
      "featured": "0",
      "content_id_count": "1"
    },
    {
      "id": "59301",
      "site_id": "873",
      "name": "German Literature & Language",
      "ordering": "0",
      "slug_id": "481006",
      "subject_id": "59301",
      "content_id": "11155855",
      "featured": "0",
      "content_id_count": "1"
    },
    {
      "id": "59307",
      "site_id": "873",
      "name": "Italian Language & Literature",
      "ordering": "0",
      "slug_id": "480998",
      "subject_id": "59307",
      "content_id": "11155855",
      "featured": "0",
      "content_id_count": "1"
    },
    {
      "id": "59309",
      "site_id": "873",
      "name": "Labor & the Left",
      "ordering": "0",
      "slug_id": "480996",
      "subject_id": "59309",
      "content_id": "11155855",
      "featured": "0",
      "content_id_count": "1"
    },
    {
      "id": "56179",
      "site_id": "873",
      "name": "Literature, Languages & Linguistics",
      "ordering": "0",
      "slug_id": "480990",
      "subject_id": "56179",
      "content_id": "11155855",
      "featured": "0",
      "content_id_count": "1"
    }
  ],
  "friendly_url": "http://guides.nyu.edu/literatureresourcecenter"
}